datacycle/__init__.py
datacycle/config.py
datacycle/main.py
datacycle/providers/gcs.py
datacycle/providers/mongo.py
datacycle/providers/postgres.py
datacycle/utils.py
datacycle/version.py
pyproject.toml
datacycle-0.0.3.dist-info/entry_points.txt
datacycle-0.0.3.dist-info/LICENSE
datacycle-0.0.3.dist-info/WHEEL
datacycle-0.0.3.dist-info/METADATA
datacycle-0.0.3.dist-info/RECORD
