Metadata-Version: 2.1
Name: datacycle
Version: 0.0.3
Summary: General toolset to backup & restore with random/filtered/anonymized data (Mongo/Postgres/GCS).
Home-page: https://github.com/smood/recycle
License: MIT
Requires-Python: >=3.8,<3.11
Classifier: License :: OSI Approved :: MIT License
Classifier: Programming Language :: Python
Classifier: Programming Language :: Python :: 3
Classifier: Programming Language :: Python :: 3.10
Classifier: Programming Language :: Python :: 3.8
Classifier: Programming Language :: Python :: 3.9
Classifier: Topic :: Software Development :: Libraries :: Python Modules
Provides-Extra: all
Provides-Extra: google
Provides-Extra: mongo
Provides-Extra: postgres
Requires-Dist: Faker (>=13.3.4,<14.0.0)
Requires-Dist: SQLAlchemy (>=1.4.13,<2.0.0); extra == "all" or extra == "postgres"
Requires-Dist: dataconf (>=1.4.0,<2.0.0)
Requires-Dist: furl (>=2.1.2,<3.0.0)
Requires-Dist: gsutil (>=5.9,<6.0); extra == "all" or extra == "google"
Requires-Dist: pg8000 (>=1.19.4,<2.0.0); extra == "all" or extra == "postgres"
Requires-Dist: pymongo (>=4.1.0,<5.0.0); extra == "all" or extra == "mongo"
Requires-Dist: sqlparse (>=0.4.1,<0.5.0)
Requires-Dist: tdqm (>=0.0.1,<0.0.2)
Requires-Dist: typer (>=0.4.1,<0.5.0)
Project-URL: Repository, https://github.com/smood/recycle
